finai_mac/__init__.py
finai_mac/__main__.py
finai_mac/jupyter_notebook_config.py
finai_mac-4.3.data/data/version.py
finai_mac-4.3.dist-info/LICENCE.txt
finai_mac-4.3.dist-info/METADATA
finai_mac-4.3.dist-info/WHEEL
finai_mac-4.3.dist-info/entry_points.txt
finai_mac-4.3.dist-info/top_level.txt
finai_mac-4.3.dist-info/RECORD
